tfplots/__init__.py
tfplots/__main__.py
tfplots-0.1.2.dist-info/WHEEL
tfplots-0.1.2.dist-info/METADATA
tfplots-0.1.2.dist-info/RECORD
